dfetch/__init__.py
dfetch/__main__.py
dfetch/log.py
dfetch/commands/__init__.py
dfetch/commands/check.py
dfetch/commands/command.py
dfetch/commands/common.py
dfetch/commands/diff.py
dfetch/commands/environment.py
dfetch/commands/freeze.py
dfetch/commands/import_.py
dfetch/commands/init.py
dfetch/commands/report.py
dfetch/commands/update.py
dfetch/commands/validate.py
dfetch/manifest/__init__.py
dfetch/manifest/manifest.py
dfetch/manifest/project.py
dfetch/manifest/remote.py
dfetch/manifest/validate.py
dfetch/manifest/version.py
dfetch/project/__init__.py
dfetch/project/abstract_check_reporter.py
dfetch/project/git.py
dfetch/project/metadata.py
dfetch/project/svn.py
dfetch/project/vcs.py
dfetch/reporting/__init__.py
dfetch/reporting/reporter.py
dfetch/reporting/sbom_reporter.py
dfetch/reporting/stdout_reporter.py
dfetch/reporting/check/__init__.py
dfetch/reporting/check/code_climate_reporter.py
dfetch/reporting/check/jenkins_reporter.py
dfetch/reporting/check/reporter.py
dfetch/reporting/check/sarif_reporter.py
dfetch/reporting/check/stdout_reporter.py
dfetch/resources/__init__.py
dfetch/resources/schema.yaml
dfetch/resources/template.yaml
dfetch/util/__init__.py
dfetch/util/cmdline.py
dfetch/util/license.py
dfetch/util/purl.py
dfetch/util/util.py
dfetch/util/versions.py
dfetch/vcs/__init__.py
dfetch/vcs/git.py
dfetch/vcs/patch.py
dfetch-0.11.0.dist-info/licenses/LICENSE
dfetch-0.11.0.dist-info/METADATA
dfetch-0.11.0.dist-info/WHEEL
dfetch-0.11.0.dist-info/entry_points.txt
dfetch-0.11.0.dist-info/top_level.txt
dfetch-0.11.0.dist-info/RECORD
